{
    "services": [
        {
            "service": "frontend",
            "history": [
                {
                    "emissions": 76.04567098195622,
                    "joules": 1462.4167496530042
                },
                {
                    "emissions": 82.48634216437844,
                    "joules": 1556.3460785731781
                },
                {
                    "emissions": 96.34661726876033,
                    "joules": 1817.860703184157
                }
            ]
        },
        {
            "service": "productcatalogservice",
            "history": [
                {
                    "emissions": 175.60035736849508,
                    "joules": 652.7894325966361
                },
                {
                    "emissions": 184.79481230638373,
                    "joules": 694.7173394976833
                },
                {
                    "emissions": 217.46900050465868,
                    "joules": 811.4514944203682
                }
            ]
        },
        {
            "service": "currencyservice",
            "history": [
                {
                    "emissions": 198.19492722301135,
                    "joules": 581.2167953753998
                },
                {
                    "emissions": 207.2134711031121,
                    "joules": 618.547674934663
                },
                {
                    "emissions": 241.30930642478253,
                    "joules": 722.4829533676124
                }
            ]
        },
        {
            "service": "recommendationservice",
            "history": [
                {
                    "emissions": 107.08044078413371,
                    "joules": 398.0685531008688
                },
                {
                    "emissions": 112.68718499737533,
                    "joules": 423.6360338247193
                },
                {
                    "emissions": 132.61178268593756,
                    "joules": 494.82008464902077
                }
            ]
        },
        {
            "service": "cartservice",
            "history": [
                {
                    "emissions": 123.0378606313656,
                    "joules": 360.81484056118944
                },
                {
                    "emissions": 128.63650213327008,
                    "joules": 383.98955860677637
                },
                {
                    "emissions": 149.80293001917317,
                    "joules": 448.5117665244706
                }
            ]
        },
        {
            "service": "adservice",
            "history": [
                {
                    "emissions": 56.578122190250554,
                    "joules": 165.91824689223037
                },
                {
                    "emissions": 59.15261935208928,
                    "joules": 176.57498314056502
                },
                {
                    "emissions": 68.88585704912433,
                    "joules": 206.24508098540218
                }
            ]
        },
        {
            "service": "checkoutservice",
            "history": [
                {
                    "emissions": 21.320313793066827,
                    "joules": 79.25767209318522
                },
                {
                    "emissions": 22.436647878997157,
                    "joules": 84.34830029698179
                },
                {
                    "emissions": 26.40374655556241,
                    "joules": 98.52144237150152
                }
            ]
        },
        {
            "service": "shippingservice",
            "history": [
                {
                    "emissions": 22.25154467368857,
                    "joules": 65.25379669703393
                },
                {
                    "emissions": 23.26406570463241,
                    "joules": 69.44497225263406
                },
                {
                    "emissions": 27.092039575997934,
                    "joules": 81.11389094610159
                }
            ]
        },
        {
            "service": "emailservice",
            "history": [
                {
                    "emissions": 11.400014768908333,
                    "joules": 33.43112835456989
                },
                {
                    "emissions": 11.918754248610108,
                    "joules": 35.57837089137346
                },
                {
                    "emissions": 13.879919610768683,
                    "joules": 41.5566455412236
                }
            ]
        },
        {
            "service": "paymentservice",
            "history": [
                {
                    "emissions": 7.863359267514214,
                    "joules": 23.059704596815877
                },
                {
                    "emissions": 8.221168882486236,
                    "joules": 24.54080263428727
                },
                {
                    "emissions": 9.57391693924461,
                    "joules": 28.664421973786254
                }
            ]
        }
    ],
    "connections": [
        {
            "source": "checkoutservice",
            "destination": "currencyservice",
            "history": [
                {
                    "emissions": 26.32445602907534,
                    "joules": 97.86043133485256
                },
                {
                    "emissions": 26.030874735070782,
                    "joules": 97.86043133485256
                },
                {
                    "emissions": 26.226595597740488,
                    "joules": 97.86043133485256
                }
            ]
        },
        {
            "source": "checkoutservice",
            "destination": "emailservice",
            "history": [
                {
                    "emissions": 40.22327794222215,
                    "joules": 149.5289142833537
                },
                {
                    "emissions": 39.77469119937208,
                    "joules": 149.52891428335369
                },
                {
                    "emissions": 40.07374902793879,
                    "joules": 149.52891428335369
                }
            ]
        },
        {
            "source": "checkoutservice",
            "destination": "paymentservice",
            "history": [
                {
                    "emissions": 11.073718647484743,
                    "joules": 41.16624032522209
                },
                {
                    "emissions": 10.950219926509076,
                    "joules": 41.16624032522209
                },
                {
                    "emissions": 11.03255240715952,
                    "joules": 41.166240325222084
                }
            ]
        },
        {
            "source": "checkoutservice",
            "destination": "productcatalogservice",
            "history": [
                {
                    "emissions": 15.805132566472183,
                    "joules": 58.75513965231295
                },
                {
                    "emissions": 15.628867147515244,
                    "joules": 58.75513965231294
                },
                {
                    "emissions": 15.746377426819869,
                    "joules": 58.75513965231294
                }
            ]
        },
        {
            "source": "checkoutservice",
            "destination": "shippingservice",
            "history": [
                {
                    "emissions": 38.979761682963336,
                    "joules": 144.90617726008676
                },
                {
                    "emissions": 38.54504315118307,
                    "joules": 144.90617726008674
                },
                {
                    "emissions": 38.834855505703246,
                    "joules": 144.90617726008674
                }
            ]
        },
        {
            "source": "frontend",
            "destination": "productcatalogservice",
            "history": [
                {
                    "emissions": 161.89314777070436,
                    "joules": 3113.329764821238
                },
                {
                    "emissions": 165.0064775355256,
                    "joules": 3113.329764821238
                },
                {
                    "emissions": 165.0064775355256,
                    "joules": 3113.329764821238
                }
            ]
        },
        {
            "source": "frontend",
            "destination": "recommendationservice",
            "history": [
                {
                    "emissions": 48.63742393094632,
                    "joules": 935.3350755951216
                },
                {
                    "emissions": 49.57275900654144,
                    "joules": 935.3350755951216
                },
                {
                    "emissions": 49.57275900654144,
                    "joules": 935.3350755951216
                }
            ]
        },
        {
            "source": "frontend",
            "destination": "shippingservice",
            "history": [
                {
                    "emissions": 11.256795812044707,
                    "joules": 216.4768425393213
                },
                {
                    "emissions": 11.473272654584028,
                    "joules": 216.4768425393213
                },
                {
                    "emissions": 11.473272654584028,
                    "joules": 216.4768425393213
                }
            ]
        },
        {
            "source": "frontend",
            "destination": "adservice",
            "history": [
                {
                    "emissions": 23.834274310438705,
                    "joules": 458.3514290468982
                },
                {
                    "emissions": 24.292625739485604,
                    "joules": 458.3514290468982
                },
                {
                    "emissions": 24.292625739485604,
                    "joules": 458.3514290468982
                }
            ]
        },
        {
            "source": "checkoutservice",
            "destination": "cartservice",
            "history": [
                {
                    "emissions": 20.52167237434533,
                    "joules": 76.28874488604212
                },
                {
                    "emissions": 20.2928061396872,
                    "joules": 76.28874488604211
                },
                {
                    "emissions": 20.445383629459286,
                    "joules": 76.28874488604211
                }
            ]
        },
        {
            "source": "frontend",
            "destination": "cartservice",
            "history": [
                {
                    "emissions": 51.43886265793136,
                    "joules": 989.2088972679107
                },
                {
                    "emissions": 52.42807155519927,
                    "joules": 989.2088972679107
                },
                {
                    "emissions": 52.42807155519927,
                    "joules": 989.2088972679107
                }
            ]
        },
        {
            "source": "frontend",
            "destination": "checkoutservice",
            "history": [
                {
                    "emissions": 5.3362255845781235,
                    "joules": 102.61972278034854
                },
                {
                    "emissions": 5.438845307358472,
                    "joules": 102.61972278034852
                },
                {
                    "emissions": 5.438845307358472,
                    "joules": 102.61972278034852
                }
            ]
        },
        {
            "source": "frontend",
            "destination": "currencyservice",
            "history": [
                {
                    "emissions": 107.81637127633144,
                    "joules": 2073.391755314066
                },
                {
                    "emissions": 109.88976303164551,
                    "joules": 2073.3917553140664
                },
                {
                    "emissions": 109.88976303164551,
                    "joules": 2073.3917553140664
                }
            ]
        },
        {
            "source": "recommendationservice",
            "destination": "productcatalogservice",
            "history": [
                {
                    "emissions": 93.64509708256517,
                    "joules": 348.12303748165493
                },
                {
                    "emissions": 92.60072797012022,
                    "joules": 348.123037481655
                },
                {
                    "emissions": 93.29697404508353,
                    "joules": 348.123037481655
                }
            ]
        }
    ],
    "constraints": [
        {
            "category": "affinity",
            "source": "frontend",
            "source_flavour": "large",
            "destination": "productcatalogservice",
            "destination_flavour": "medium",
            "constraint_weight": 0.8168379990298148,
            "weight": 1.0
        },
        {
            "category": "affinity",
            "source": "frontend",
            "source_flavour": "large",
            "destination": "currencyservice",
            "destination_flavour": "small",
            "constraint_weight": 0.5439915783263976,
            "weight": 1.0
        },
        {
            "category": "affinity",
            "source": "recommendationservice",
            "source_flavour": "large",
            "destination": "productcatalogservice",
            "destination_flavour": "medium",
            "constraint_weight": 0.472489878498225,
            "weight": 1.0
        }
    ]
}